Flask_RESTful_DRY-0.3.1.dist-info/DESCRIPTION.rst
Flask_RESTful_DRY-0.3.1.dist-info/metadata.json
Flask_RESTful_DRY-0.3.1.dist-info/METADATA
Flask_RESTful_DRY-0.3.1.dist-info/top_level.txt
Flask_RESTful_DRY-0.3.1.dist-info/WHEEL
Flask_RESTful_DRY-0.3.1.dist-info/RECORD
flask_dry/__init__.py
flask_dry/model/translate_errors.py
flask_dry/model/validation.py
flask_dry/model/column_info.py
flask_dry/model/columns.py
flask_dry/model/model.py
flask_dry/model/__init__.py
flask_dry/model/utils.py
flask_dry/model/__pycache__/columns.cpython-34.pyc
flask_dry/model/__pycache__/model.cpython-34.pyc
flask_dry/model/__pycache__/validation.cpython-34.pyc
flask_dry/model/__pycache__/utils.cpython-34.pyc
flask_dry/model/__pycache__/__init__.cpython-34.pyc
flask_dry/model/__pycache__/column_info.cpython-34.pyc
flask_dry/model/__pycache__/translate_errors.cpython-34.pyc
flask_dry/__pycache__/__init__.cpython-34.pyc
flask_dry/api/updated_items.py
flask_dry/api/query_categories.py
flask_dry/api/step_utils.py
flask_dry/api/passwords.py
flask_dry/api/list_resource.py
flask_dry/api/steps.py
flask_dry/api/http_methods.py
flask_dry/api/column_auth.py
flask_dry/api/item_resource.py
flask_dry/api/dry_resource.py
flask_dry/api/class_init.py
flask_dry/api/allow.py
flask_dry/api/links.py
flask_dry/api/authorization.py
flask_dry/api/api.py
flask_dry/api/app.py
flask_dry/api/__init__.py
flask_dry/api/utils.py
flask_dry/api/__pycache__/authorization.cpython-34.pyc
flask_dry/api/__pycache__/updated_items.cpython-34.pyc
flask_dry/api/__pycache__/http_methods.cpython-34.pyc
flask_dry/api/__pycache__/list_resource.cpython-34.pyc
flask_dry/api/__pycache__/dry_resource.cpython-34.pyc
flask_dry/api/__pycache__/links.cpython-34.pyc
flask_dry/api/__pycache__/app.cpython-34.pyc
flask_dry/api/__pycache__/step_utils.cpython-34.pyc
flask_dry/api/__pycache__/column_auth.cpython-34.pyc
flask_dry/api/__pycache__/item_resource.cpython-34.pyc
flask_dry/api/__pycache__/query_categories.cpython-34.pyc
flask_dry/api/__pycache__/passwords.cpython-34.pyc
flask_dry/api/__pycache__/utils.cpython-34.pyc
flask_dry/api/__pycache__/api.cpython-34.pyc
flask_dry/api/__pycache__/__init__.cpython-34.pyc
