Metadata-Version: 2.0
Name: Flask-RESTful-DRY
Version: 0.3.1
Summary: Flask-RESTful APIs using declarations, not code
Home-page: https://bitbucket.org/dangyogi/flask-restful-dry
Author: Bruce Frederiksen
Author-email: dangyogi@gmail.com
License: MIT
Keywords: Flask RESTful Flask-RESTful DRY declarations web
Platform: UNKNOWN
Classifier: Development Status :: 2 - Pre-Alpha
Classifier: Framework :: Flask
Classifier: Intended Audience :: Developers
Classifier: License :: OSI Approved :: MIT License
Classifier: Operating System :: OS Independent
Classifier: Programming Language :: Python :: 3.4
Requires-Dist: flask (>=0.10.1)
Requires-Dist: Flask-Login (>=0.2.11)
Requires-Dist: Flask-RESTful (>=0.2.12)
Requires-Dist: Flask-WTF (>=0.10.0)
Requires-Dist: Flask-SQLAlchemy (>=1.0)
Requires-Dist: SQLAlchemy (>=0.9.7)
Requires-Dist: passlib (>=1.6.2)
Requires-Dist: pytest (>=2.6.1)
Requires-Dist: Sphinx (>=1.2.2)
